{
    "inscription": "",
    "medium": "Oil paint on canvas",
    "dimensions": "support: 613 x 762 mm frame: 755 x 613 x 72 mm",
    "title": "A Representation of the Liberal Arts: Ceiling Design for the State Dining Room at Grimsthorpe Castle",
    "thumbnailUrl": "http://www.tate.org.uk/art/images/work/T/T03/T03465_8.jpg",
    "artistRole": "artist",
    "accession_number": "T03465",
    "depth": null,
    "height": 762,
    "acquisitionYear": 1982,
    "artistId": 500,
    "width": 613,
    "url": "http://www.tate.org.uk/art/artworks/sleter-a-representation-of-the-liberal-arts-ceiling-design-for-the-state-dining-room-at-t03465",
    "thumbnailCopyright": "",
    "year": 1724,
    "units": "mm",
    "dateText": "c.1724",
    "artist": "Sleter, Francesco",
    "id": 13463,
    "creditLine": "Purchased 1982"
}